{"33": {"AA": "impossible", "AK": "rfi-1", "AQ": "fold", "AJ": "fold", "AT": "fold", "A9": "fold", "A8": "fold", "A7": "fold", "A6": "fold", "A5": "fold", "A4": "fold", "A3": "impossible", "A2": "impossible", "KK": "impossible", "KQ": "fold", "KJ": "fold", "KT": "fold", "K9": "fold", "K8": "fold", "K7": "fold", "K6": "fold", "K5": "fold", "K4": "fold", "K3": "impossible", "K2": "impossible", "QQ": "impossible", "QJ": "fold", "QT": "fold", "Q9": "fold", "Q8": "fold", "Q7": "fold", "Q6": "fold", "Q5": "fold", "Q4": "fold", "Q3": "impossible", "Q2": "impossible", "JJ": "impossible", "JT": "fold", "J9": "fold", "J8": "fold", "J7": "fold", "J6": "fold", "J5": "fold", "J4": "fold", "J3": "impossible", "J2": "impossible", "TT": "impossible", "T9": "fold", "T8": "fold", "T7": "fold", "T6": "fold", "T5": "fold", "T4": "fold", "T3": "impossible", "T2": "impossible", "99": "impossible", "98": "fold", "97": "fold", "96": "fold", "95": "fold", "94": "fold", "93": "impossible", "92": "impossible", "88": "impossible", "87": "fold", "86": "fold", "85": "fold", "84": "fold", "83": "impossible", "82": "impossible", "77": "impossible", "76": "fold", "75": "fold", "74": "fold", "73": "impossible", "72": "impossible", "66": "impossible", "65": "rfi-0", "64": "fold", "63": "impossible", "62": "impossible", "55": "impossible", "54": "fold", "53": "impossible", "52": "impossible", "44": "impossible", "43": "impossible", "42": "impossible", "33": "impossible", "32": "impossible", "22": "rfi-3"}, "22": {"AA": "impossible", "AK": "rfi-1", "AQ": "fold", "AJ": "fold", "AT": "fold", "A9": "fold", "A8": "fold", "A7": "fold", "A6": "fold", "A5": "fold", "A4": "fold", "A3": "fold", "A2": "impossible", "KK": "impossible", "KQ": "fold", "KJ": "fold", "KT": "fold", "K9": "fold", "K8": "fold", "K7": "fold", "K6": "fold", "K5": "fold", "K4": "fold", "K3": "fold", "K2": "impossible", "QQ": "impossible", "QJ": "fold", "QT": "fold", "Q9": "fold", "Q8": "fold", "Q7": "fold", "Q6": "fold", "Q5": "fold", "Q4": "fold", "Q3": "fold", "Q2": "impossible", "JJ": "impossible", "JT": "fold", "J9": "fold", "J8": "fold", "J7": "fold", "J6": "fold", "J5": "fold", "J4": "fold", "J3": "fold", "J2": "impossible", "TT": "impossible", "T9": "fold", "T8": "fold", "T7": "fold", "T6": "fold", "T5": "fold", "T4": "fold", "T3": "fold", "T2": "impossible", "99": "impossible", "98": "fold", "97": "fold", "96": "fold", "95": "fold", "94": "fold", "93": "fold", "92": "impossible", "88": "impossible", "87": "fold", "86": "fold", "85": "fold", "84": "fold", "83": "fold", "82": "impossible", "77": "impossible", "76": "fold", "75": "fold", "74": "fold", "73": "fold", "72": "impossible", "66": "impossible", "65": "fold", "64": "fold", "63": "fold", "62": "impossible", "55": "impossible", "54": "fold", "53": "fold", "52": "impossible", "44": "impossible", "43": "fold", "42": "impossible", "33": "impossible", "32": "impossible", "22": "impossible"}, "44": {"AA": "impossible", "AK": "rfi-1", "AQ": "fold", "AJ": "fold", "AT": "fold", "A9": "fold", "A8": "fold", "A7": "fold", "A6": "fold", "A5": "fold", "A4": "impossible", "A3": "impossible", "A2": "impossible", "KK": "impossible", "KQ": "fold", "KJ": "fold", "KT": "fold", "K9": "fold", "K8": "fold", "K7": "fold", "K6": "fold", "K5": "fold", "K4": "impossible", "K3": "impossible", "K2": "impossible", "QQ": "impossible", "QJ": "fold", "QT": "fold", "Q9": "fold", "Q8": "fold", "Q7": "fold", "Q6": "fold", "Q5": "fold", "Q4": "impossible", "Q3": "impossible", "Q2": "impossible", "JJ": "impossible", "JT": "fold", "J9": "fold", "J8": "fold", "J7": "fold", "J6": "fold", "J5": "fold", "J4": "impossible", "J3": "impossible", "J2": "impossible", "TT": "impossible", "T9": "fold", "T8": "fold", "T7": "fold", "T6": "fold", "T5": "fold", "T4": "impossible", "T3": "impossible", "T2": "impossible", "99": "impossible", "98": "fold", "97": "fold", "96": "fold", "95": "fold", "94": "impossible", "93": "impossible", "92": "impossible", "88": "impossible", "87": "fold", "86": "fold", "85": "fold", "84": "impossible", "83": "impossible", "82": "impossible", "77": "impossible", "76": "fold", "75": "fold", "74": "impossible", "73": "impossible", "72": "impossible", "66": "impossible", "65": "rfi-0", "64": "impossible", "63": "impossible", "62": "impossible", "55": "impossible", "54": "impossible", "53": "impossible", "52": "impossible", "44": "impossible", "43": "impossible", "42": "impossible", "33": "rfi-4", "32": "fold", "22": "rfi-3"}, "55": {"AA": "impossible", "AK": "rfi-1", "AQ": "fold", "AJ": "fold", "AT": "fold", "A9": "fold", "A8": "fold", "A7": "fold", "A6": "fold", "A5": "impossible", "A4": "impossible", "A3": "impossible", "A2": "impossible", "KK": "impossible", "KQ": "fold", "KJ": "fold", "KT": "fold", "K9": "fold", "K8": "fold", "K7": "fold", "K6": "fold", "K5": "impossible", "K4": "impossible", "K3": "impossible", "K2": "impossible", "QQ": "impossible", "QJ": "fold", "QT": "fold", "Q9": "fold", "Q8": "fold", "Q7": "fold", "Q6": "fold", "Q5": "impossible", "Q4": "impossible", "Q3": "impossible", "Q2": "impossible", "JJ": "impossible", "JT": "fold", "J9": "fold", "J8": "fold", "J7": "fold", "J6": "fold", "J5": "impossible", "J4": "impossible", "J3": "impossible", "J2": "impossible", "TT": "impossible", "T9": "fold", "T8": "fold", "T7": "fold", "T6": "fold", "T5": "impossible", "T4": "impossible", "T3": "impossible", "T2": "impossible", "99": "impossible", "98": "fold", "97": "fold", "96": "fold", "95": "impossible", "94": "impossible", "93": "impossible", "92": "impossible", "88": "impossible", "87": "fold", "86": "fold", "85": "impossible", "84": "impossible", "83": "impossible", "82": "impossible", "77": "impossible", "76": "rfi-0", "75": "impossible", "74": "impossible", "73": "impossible", "72": "impossible", "66": "impossible", "65": "impossible", "64": "impossible", "63": "impossible", "62": "impossible", "55": "impossible", "54": "impossible", "53": "impossible", "52": "impossible", "44": "rfi-4", "43": "fold", "42": "fold", "33": "rfi-4", "32": "fold", "22": "rfi-3"}, "66": {"AA": "impossible", "AK": "rfi-0", "AQ": "fold", "AJ": "fold", "AT": "fold", "A9": "fold", "A8": "fold", "A7": "fold", "A6": "impossible", "A5": "impossible", "A4": "impossible", "A3": "impossible", "A2": "impossible", "KK": "impossible", "KQ": "fold", "KJ": "fold", "KT": "fold", "K9": "fold", "K8": "fold", "K7": "fold", "K6": "impossible", "K5": "impossible", "K4": "impossible", "K3": "impossible", "K2": "impossible", "QQ": "impossible", "QJ": "fold", "QT": "fold", "Q9": "fold", "Q8": "fold", "Q7": "fold", "Q6": "impossible", "Q5": "impossible", "Q4": "impossible", "Q3": "impossible", "Q2": "impossible", "JJ": "impossible", "JT": "fold", "J9": "fold", "J8": "fold", "J7": "fold", "J6": "impossible", "J5": "impossible", "J4": "impossible", "J3": "impossible", "J2": "impossible", "TT": "impossible", "T9": "fold", "T8": "fold", "T7": "fold", "T6": "impossible", "T5": "impossible", "T4": "impossible", "T3": "impossible", "T2": "impossible", "99": "impossible", "98": "fold", "97": "fold", "96": "impossible", "95": "impossible", "94": "impossible", "93": "impossible", "92": "impossible", "88": "impossible", "87": "rfi-0", "86": "impossible", "85": "impossible", "84": "impossible", "83": "impossible", "82": "impossible", "77": "impossible", "76": "impossible", "75": "impossible", "74": "impossible", "73": "impossible", "72": "impossible", "66": "impossible", "65": "impossible", "64": "impossible", "63": "impossible", "62": "impossible", "55": "rfi-5", "54": "rfi-1", "53": "rfi-0", "52": "fold", "44": "rfi-4", "43": "fold", "42": "fold", "33": "rfi-3", "32": "fold", "22": "rfi-1"}, "77": {"AA": "impossible", "AK": "rfi-0", "AQ": "fold", "AJ": "fold", "AT": "rfi-0", "A9": "fold", "A8": "fold", "A7": "impossible", "A6": "impossible", "A5": "impossible", "A4": "impossible", "A3": "impossible", "A2": "impossible", "KK": "impossible", "KQ": "fold", "KJ": "fold", "KT": "fold", "K9": "fold", "K8": "fold", "K7": "impossible", "K6": "impossible", "K5": "impossible", "K4": "impossible", "K3": "impossible", "K2": "impossible", "QQ": "impossible", "QJ": "fold", "QT": "fold", "Q9": "fold", "Q8": "fold", "Q7": "impossible", "Q6": "impossible", "Q5": "impossible", "Q4": "impossible", "Q3": "impossible", "Q2": "impossible", "JJ": "impossible", "JT": "fold", "J9": "fold", "J8": "fold", "J7": "impossible", "J6": "impossible", "J5": "impossible", "J4": "impossible", "J3": "impossible", "J2": "impossible", "TT": "impossible", "T9": "fold", "T8": "rfi-0", "T7": "impossible", "T6": "impossible", "T5": "impossible", "T4": "impossible", "T3": "impossible", "T2": "impossible", "99": "impossible", "98": "rfi-0", "97": "impossible", "96": "impossible", "95": "impossible", "94": "impossible", "93": "impossible", "92": "impossible", "88": "impossible", "87": "impossible", "86": "impossible", "85": "impossible", "84": "impossible", "83": "impossible", "82": "impossible", "77": "impossible", "76": "impossible", "75": "impossible", "74": "impossible", "73": "impossible", "72": "impossible", "66": "rfi-5", "65": "rfi-0", "64": "fold", "63": "fold", "62": "fold", "55": "rfi-3", "54": "fold", "53": "fold", "52": "fold", "44": "rfi-2", "43": "fold", "42": "fold", "33": "rfi-1", "32": "fold", "22": "fold"}, "88": {"AA": "impossible", "AK": "rfi-1", "AQ": "rfi-0", "AJ": "rfi-0", "AT": "rfi-1", "A9": "rfi-0", "A8": "impossible", "A7": "impossible", "A6": "impossible", "A5": "impossible", "A4": "impossible", "A3": "impossible", "A2": "impossible", "KK": "impossible", "KQ": "fold", "KJ": "fold", "KT": "rfi-0", "K9": "fold", "K8": "impossible", "K7": "impossible", "K6": "impossible", "K5": "impossible", "K4": "impossible", "K3": "impossible", "K2": "impossible", "QQ": "impossible", "QJ": "fold", "QT": "rfi-0", "Q9": "fold", "Q8": "impossible", "Q7": "impossible", "Q6": "impossible", "Q5": "impossible", "Q4": "impossible", "Q3": "impossible", "Q2": "impossible", "JJ": "impossible", "JT": "rfi-1", "J9": "rfi-0", "J8": "impossible", "J7": "impossible", "J6": "impossible", "J5": "impossible", "J4": "impossible", "J3": "impossible", "J2": "impossible", "TT": "impossible", "T9": "rfi-0", "T8": "impossible", "T7": "impossible", "T6": "impossible", "T5": "impossible", "T4": "impossible", "T3": "impossible", "T2": "impossible", "99": "impossible", "98": "impossible", "97": "impossible", "96": "impossible", "95": "impossible", "94": "impossible", "93": "impossible", "92": "impossible", "88": "impossible", "87": "impossible", "86": "impossible", "85": "impossible", "84": "impossible", "83": "impossible", "82": "impossible", "77": "rfi-5", "76": "rfi-0", "75": "rfi-0", "74": "fold", "73": "fold", "72": "fold", "66": "rfi-4", "65": "rfi-0", "64": "fold", "63": "fold", "62": "fold", "55": "rfi-2", "54": "fold", "53": "fold", "52": "fold", "44": "rfi-1", "43": "fold", "42": "fold", "33": "rfi-0", "32": "fold", "22": "rfi-0"}, "99": {"AA": "impossible", "AK": "rfi-2", "AQ": "rfi-1", "AJ": "rfi-1", "AT": "rfi-2", "A9": "impossible", "A8": "impossible", "A7": "impossible", "A6": "impossible", "A5": "impossible", "A4": "impossible", "A3": "impossible", "A2": "impossible", "KK": "impossible", "KQ": "rfi-0", "KJ": "rfi-0", "KT": "rfi-1", "K9": "impossible", "K8": "impossible", "K7": "impossible", "K6": "impossible", "K5": "impossible", "K4": "impossible", "K3": "impossible", "K2": "impossible", "QQ": "impossible", "QJ": "rfi-0", "QT": "rfi-1", "Q9": "impossible", "Q8": "impossible", "Q7": "impossible", "Q6": "impossible", "Q5": "impossible", "Q4": "impossible", "Q3": "impossible", "Q2": "impossible", "JJ": "impossible", "JT": "rfi-2", "J9": "impossible", "J8": "impossible", "J7": "impossible", "J6": "impossible", "J5": "impossible", "J4": "impossible", "J3": "impossible", "J2": "impossible", "TT": "impossible", "T9": "impossible", "T8": "impossible", "T7": "impossible", "T6": "impossible", "T5": "impossible", "T4": "impossible", "T3": "impossible", "T2": "impossible", "99": "impossible", "98": "impossible", "97": "impossible", "96": "impossible", "95": "impossible", "94": "impossible", "93": "impossible", "92": "impossible", "88": "rfi-5", "87": "rfi-0", "86": "rfi-0", "85": "fold", "84": "fold", "83": "fold", "82": "fold", "77": "rfi-4", "76": "rfi-0", "75": "fold", "74": "fold", "73": "fold", "72": "fold", "66": "rfi-3", "65": "fold", "64": "fold", "63": "fold", "62": "fold", "55": "rfi-1", "54": "fold", "53": "fold", "52": "fold", "44": "rfi-0", "43": "fold", "42": "fold", "33": "rfi-1", "32": "fold", "22": "rfi-1"}, "TT": {"AA": "impossible", "AK": "rfi-4", "AQ": "rfi-3", "AJ": "rfi-3", "AT": "impossible", "A9": "impossible", "A8": "impossible", "A7": "impossible", "A6": "impossible", "A5": "impossible", "A4": "impossible", "A3": "impossible", "A2": "impossible", "KK": "impossible", "KQ": "rfi-2", "KJ": "rfi-3", "KT": "impossible", "K9": "impossible", "K8": "impossible", "K7": "impossible", "K6": "impossible", "K5": "impossible", "K4": "impossible", "K3": "impossible", "K2": "impossible", "QQ": "impossible", "QJ": "rfi-3", "QT": "impossible", "Q9": "impossible", "Q8": "impossible", "Q7": "impossible", "Q6": "impossible", "Q5": "impossible", "Q4": "impossible", "Q3": "impossible", "Q2": "impossible", "JJ": "impossible", "JT": "impossible", "J9": "impossible", "J8": "impossible", "J7": "impossible", "J6": "impossible", "J5": "impossible", "J4": "impossible", "J3": "impossible", "J2": "impossible", "TT": "impossible", "T9": "impossible", "T8": "impossible", "T7": "impossible", "T6": "impossible", "T5": "impossible", "T4": "impossible", "T3": "impossible", "T2": "impossible", "99": "rfi-5", "98": "rfi-2", "97": "rfi-1", "96": "rfi-0", "95": "fold", "94": "fold", "93": "fold", "92": "fold", "88": "rfi-5", "87": "rfi-1", "86": "rfi-0", "85": "fold", "84": "fold", "83": "fold", "82": "fold", "77": "rfi-4", "76": "rfi-0", "75": "fold", "74": "fold", "73": "fold", "72": "fold", "66": "rfi-3", "65": "fold", "64": "fold", "63": "fold", "62": "fold", "55": "rfi-1", "54": "fold", "53": "fold", "52": "fold", "44": "rfi-2", "43": "fold", "42": "fold", "33": "rfi-2", "32": "fold", "22": "rfi-2"}, "JJ": {"AA": "impossible", "AK": "rfi-5", "AQ": "rfi-4", "AJ": "impossible", "AT": "impossible", "A9": "impossible", "A8": "impossible", "A7": "impossible", "A6": "impossible", "A5": "impossible", "A4": "impossible", "A3": "impossible", "A2": "impossible", "KK": "impossible", "KQ": "rfi-3", "KJ": "impossible", "KT": "impossible", "K9": "impossible", "K8": "impossible", "K7": "impossible", "K6": "impossible", "K5": "impossible", "K4": "impossible", "K3": "impossible", "K2": "impossible", "QQ": "impossible", "QJ": "impossible", "QT": "impossible", "Q9": "impossible", "Q8": "impossible", "Q7": "impossible", "Q6": "impossible", "Q5": "impossible", "Q4": "impossible", "Q3": "impossible", "Q2": "impossible", "JJ": "impossible", "JT": "impossible", "J9": "impossible", "J8": "impossible", "J7": "impossible", "J6": "impossible", "J5": "impossible", "J4": "impossible", "J3": "impossible", "J2": "impossible", "TT": "rfi-5", "T9": "rfi-3", "T8": "rfi-2", "T7": "rfi-1", "T6": "rfi-0", "T5": "rfi-0", "T4": "rfi-0", "T3": "rfi-0", "T2": "rfi-0", "99": "rfi-5", "98": "rfi-1", "97": "rfi-1", "96": "fold", "95": "fold", "94": "fold", "93": "fold", "92": "fold", "88": "rfi-4", "87": "rfi-0", "86": "fold", "85": "fold", "84": "fold", "83": "fold", "82": "fold", "77": "rfi-3", "76": "fold", "75": "fold", "74": "fold", "73": "fold", "72": "fold", "66": "rfi-2", "65": "fold", "64": "fold", "63": "fold", "62": "fold", "55": "rfi-2", "54": "fold", "53": "fold", "52": "fold", "44": "rfi-2", "43": "fold", "42": "fold", "33": "rfi-3", "32": "fold", "22": "rfi-3"}, "QQ": {"AA": "impossible", "AK": "rfi-5", "AQ": "impossible", "AJ": "impossible", "AT": "impossible", "A9": "impossible", "A8": "impossible", "A7": "impossible", "A6": "impossible", "A5": "impossible", "A4": "impossible", "A3": "impossible", "A2": "impossible", "KK": "impossible", "KQ": "impossible", "KJ": "impossible", "KT": "impossible", "K9": "impossible", "K8": "impossible", "K7": "impossible", "K6": "impossible", "K5": "impossible", "K4": "impossible", "K3": "impossible", "K2": "impossible", "QQ": "impossible", "QJ": "impossible", "QT": "impossible", "Q9": "impossible", "Q8": "impossible", "Q7": "impossible", "Q6": "impossible", "Q5": "impossible", "Q4": "impossible", "Q3": "impossible", "Q2": "impossible", "JJ": "rfi-5", "JT": "rfi-4", "J9": "rfi-2", "J8": "rfi-1", "J7": "rfi-0", "J6": "rfi-1", "J5": "rfi-1", "J4": "rfi-1", "J3": "rfi-1", "J2": "rfi-1", "TT": "rfi-5", "T9": "rfi-3", "T8": "rfi-3", "T7": "rfi-1", "T6": "rfi-1", "T5": "rfi-1", "T4": "rfi-1", "T3": "rfi-0", "T2": "rfi-1", "99": "rfi-5", "98": "rfi-2", "97": "rfi-1", "96": "rfi-0", "95": "rfi-0", "94": "fold", "93": "fold", "92": "fold", "88": "rfi-4", "87": "rfi-1", "86": "rfi-0", "85": "rfi-0", "84": "fold", "83": "fold", "82": "fold", "77": "rfi-3", "76": "rfi-1", "75": "rfi-0", "74": "fold", "73": "fold", "72": "fold", "66": "rfi-3", "65": "rfi-0", "64": "rfi-0", "63": "fold", "62": "fold", "55": "rfi-3", "54": "rfi-1", "53": "rfi-0", "52": "fold", "44": "rfi-3", "43": "fold", "42": "fold", "33": "rfi-4", "32": "fold", "22": "rfi-4"}, "KK": {"AA": "impossible", "AK": "impossible", "AQ": "impossible", "AJ": "impossible", "AT": "impossible", "A9": "impossible", "A8": "impossible", "A7": "impossible", "A6": "impossible", "A5": "impossible", "A4": "impossible", "A3": "impossible", "A2": "impossible", "KK": "impossible", "KQ": "impossible", "KJ": "impossible", "KT": "impossible", "K9": "impossible", "K8": "impossible", "K7": "impossible", "K6": "impossible", "K5": "impossible", "K4": "impossible", "K3": "impossible", "K2": "impossible", "QQ": "rfi-5", "QJ": "rfi-4", "QT": "rfi-5", "Q9": "rfi-3", "Q8": "rfi-2", "Q7": "rfi-2", "Q6": "rfi-2", "Q5": "rfi-2", "Q4": "rfi-2", "Q3": "rfi-2", "Q2": "rfi-2", "JJ": "rfi-5", "JT": "rfi-5", "J9": "rfi-4", "J8": "rfi-3", "J7": "rfi-3", "J6": "rfi-2", "J5": "rfi-2", "J4": "rfi-2", "J3": "rfi-2", "J2": "rfi-3", "TT": "rfi-5", "T9": "rfi-5", "T8": "rfi-4", "T7": "rfi-3", "T6": "rfi-3", "T5": "rfi-2", "T4": "rfi-2", "T3": "rfi-3", "T2": "rfi-3", "99": "rfi-5", "98": "rfi-3", "97": "rfi-3", "96": "rfi-2", "95": "rfi-2", "94": "rfi-1", "93": "rfi-1", "92": "rfi-1", "88": "rfi-5", "87": "rfi-3", "86": "rfi-3", "85": "rfi-2", "84": "rfi-1", "83": "rfi-1", "82": "rfi-1", "77": "rfi-5", "76": "rfi-4", "75": "rfi-3", "74": "rfi-2", "73": "rfi-1", "72": "rfi-0", "66": "rfi-5", "65": "rfi-4", "64": "rfi-3", "63": "rfi-2", "62": "rfi-1", "55": "rfi-5", "54": "rfi-4", "53": "rfi-3", "52": "rfi-2", "44": "rfi-5", "43": "rfi-3", "42": "rfi-2", "33": "rfi-5", "32": "rfi-2", "22": "rfi-5"}, "AA": {"AA": "impossible", "AK": "impossible", "AQ": "impossible", "AJ": "impossible", "AT": "impossible", "A9": "impossible", "A8": "impossible", "A7": "impossible", "A6": "impossible", "A5": "impossible", "A4": "impossible", "A3": "impossible", "A2": "impossible", "KK": "rfi-5", "KQ": "rfi-5", "KJ": "rfi-5", "KT": "rfi-5", "K9": "rfi-5", "K8": "rfi-5", "K7": "rfi-5", "K6": "rfi-5", "K5": "rfi-5", "K4": "rfi-5", "K3": "rfi-5", "K2": "rfi-5", "QQ": "rfi-5", "QJ": "rfi-5", "QT": "rfi-5", "Q9": "rfi-5", "Q8": "rfi-5", "Q7": "rfi-5", "Q6": "rfi-5", "Q5": "rfi-5", "Q4": "rfi-5", "Q3": "rfi-5", "Q2": "rfi-5", "JJ": "rfi-5", "JT": "rfi-5", "J9": "rfi-5", "J8": "rfi-5", "J7": "rfi-5", "J6": "rfi-5", "J5": "rfi-5", "J4": "rfi-5", "J3": "rfi-5", "J2": "rfi-5", "TT": "rfi-5", "T9": "rfi-5", "T8": "rfi-5", "T7": "rfi-5", "T6": "rfi-5", "T5": "rfi-5", "T4": "rfi-5", "T3": "rfi-5", "T2": "rfi-5", "99": "rfi-5", "98": "rfi-5", "97": "rfi-5", "96": "rfi-5", "95": "rfi-5", "94": "rfi-5", "93": "rfi-5", "92": "rfi-5", "88": "rfi-5", "87": "rfi-5", "86": "rfi-5", "85": "rfi-5", "84": "rfi-5", "83": "rfi-5", "82": "rfi-5", "77": "rfi-5", "76": "rfi-5", "75": "rfi-5", "74": "rfi-5", "73": "rfi-5", "72": "rfi-5", "66": "rfi-5", "65": "rfi-5", "64": "rfi-5", "63": "rfi-5", "62": "rfi-5", "55": "rfi-5", "54": "rfi-5", "53": "rfi-5", "52": "rfi-5", "44": "rfi-5", "43": "rfi-5", "42": "rfi-5", "33": "rfi-5", "32": "rfi-5", "22": "rfi-5"}}